certbot_dns_constellix/__init__.py
certbot_dns_constellix/dns_constellix.py
certbot_dns_constellix-0.3.1.dist-info/LICENSE.txt
certbot_dns_constellix-0.3.1.dist-info/METADATA
certbot_dns_constellix-0.3.1.dist-info/WHEEL
certbot_dns_constellix-0.3.1.dist-info/entry_points.txt
certbot_dns_constellix-0.3.1.dist-info/top_level.txt
certbot_dns_constellix-0.3.1.dist-info/RECORD
